{
    "MANAUS_Agriculture":{
        "MANAUS_Agriculture":0.0011652004,
        "MANAUS_Mining":0.000524637,
        "MANAUS_Manufacturing":0.0005804028,
        "MANAUS_Utilities":0.0000464453,
        "MANAUS_Construction":0.0000223438,
        "MANAUS_Trade":0.0003586215,
        "MANAUS_Transport":0.0000043311,
        "MANAUS_Business":0.0000008344,
        "MANAUS_Financial":0.0000022169,
        "MANAUS_RealEstate":0.0000177418,
        "MANAUS_OtherServices":0.0000383979,
        "MANAUS_Government":0.0000500541,
        "RestBR_Agriculture":0.0234346885,
        "RestBR_Mining":0.0,
        "RestBR_Manufacturing":0.0655610048,
        "RestBR_Utilities":0.0,
        "RestBR_Construction":0.0022850788,
        "RestBR_Trade":0.0050465354,
        "RestBR_Transport":0.0004871312,
        "RestBR_Business":0.0002283361,
        "RestBR_Financial":0.0000468059,
        "RestBR_RealEstate":0.0,
        "RestBR_OtherServices":0.0039399975,
        "RestBR_Government":0.0006706251
    },
    "MANAUS_Mining":{
        "MANAUS_Agriculture":0.0003398223,
        "MANAUS_Mining":0.0003565277,
        "MANAUS_Manufacturing":0.0000728313,
        "MANAUS_Utilities":0.0003408007,
        "MANAUS_Construction":0.0000222685,
        "MANAUS_Trade":0.0000016895,
        "MANAUS_Transport":0.0000004928,
        "MANAUS_Business":0.000000229,
        "MANAUS_Financial":0.0000006346,
        "MANAUS_RealEstate":0.0000461656,
        "MANAUS_OtherServices":0.0000004168,
        "MANAUS_Government":0.0000021424,
        "RestBR_Agriculture":0.0008774398,
        "RestBR_Mining":0.0513448008,
        "RestBR_Manufacturing":0.041279706,
        "RestBR_Utilities":0.011524249,
        "RestBR_Construction":0.0110281318,
        "RestBR_Trade":0.0001777411,
        "RestBR_Transport":0.0002782106,
        "RestBR_Business":0.0002867264,
        "RestBR_Financial":0.0000759199,
        "RestBR_RealEstate":0.0004886266,
        "RestBR_OtherServices":0.0002037438,
        "RestBR_Government":0.000271932
    },
    "MANAUS_Manufacturing":{
        "MANAUS_Agriculture":0.20642303,
        "MANAUS_Mining":0.110894505,
        "MANAUS_Manufacturing":0.273069483,
        "MANAUS_Utilities":0.075992549,
        "MANAUS_Construction":0.205220303,
        "MANAUS_Trade":0.057380844,
        "MANAUS_Transport":0.182534981,
        "MANAUS_Business":0.017316721,
        "MANAUS_Financial":0.009685629,
        "MANAUS_RealEstate":0.009289329,
        "MANAUS_OtherServices":0.071106355,
        "MANAUS_Government":0.025899345,
        "RestBR_Agriculture":0.0,
        "RestBR_Mining":0.0,
        "RestBR_Manufacturing":0.0,
        "RestBR_Utilities":0.0,
        "RestBR_Construction":0.0,
        "RestBR_Trade":0.0,
        "RestBR_Transport":0.0,
        "RestBR_Business":0.0136227048,
        "RestBR_Financial":0.0,
        "RestBR_RealEstate":0.0,
        "RestBR_OtherServices":0.0018682104,
        "RestBR_Government":0.0
    },
    "MANAUS_Utilities":{
        "MANAUS_Agriculture":0.023301242,
        "MANAUS_Mining":0.010807605,
        "MANAUS_Manufacturing":0.0015821306,
        "MANAUS_Utilities":0.1068829606,
        "MANAUS_Construction":0.0001368768,
        "MANAUS_Trade":0.0092973272,
        "MANAUS_Transport":0.0005898191,
        "MANAUS_Business":0.0003397493,
        "MANAUS_Financial":0.0019649598,
        "MANAUS_RealEstate":0.001259522,
        "MANAUS_OtherServices":0.0019901496,
        "MANAUS_Government":0.0074277449,
        "RestBR_Agriculture":0.0,
        "RestBR_Mining":0.0,
        "RestBR_Manufacturing":0.0134756281,
        "RestBR_Utilities":0.171122959,
        "RestBR_Construction":0.0010507067,
        "RestBR_Trade":0.0104959258,
        "RestBR_Transport":0.005002402,
        "RestBR_Business":0.0069298711,
        "RestBR_Financial":0.0031809453,
        "RestBR_RealEstate":0.0,
        "RestBR_OtherServices":0.0152963873,
        "RestBR_Government":0.0083734147
    },
    "MANAUS_Construction":{
        "MANAUS_Agriculture":0.000592695,
        "MANAUS_Mining":0.012571096,
        "MANAUS_Manufacturing":0.000917125,
        "MANAUS_Utilities":0.012761137,
        "MANAUS_Construction":0.093540153,
        "MANAUS_Trade":0.001035306,
        "MANAUS_Transport":0.003140253,
        "MANAUS_Business":0.0088196064,
        "MANAUS_Financial":0.002982811,
        "MANAUS_RealEstate":0.002920853,
        "MANAUS_OtherServices":0.003560329,
        "MANAUS_Government":0.013924249,
        "RestBR_Agriculture":0.0,
        "RestBR_Mining":0.0,
        "RestBR_Manufacturing":0.0,
        "RestBR_Utilities":0.0,
        "RestBR_Construction":0.0,
        "RestBR_Trade":0.0,
        "RestBR_Transport":0.0,
        "RestBR_Business":0.0052151013,
        "RestBR_Financial":0.0,
        "RestBR_RealEstate":0.0,
        "RestBR_OtherServices":0.0,
        "RestBR_Government":0.0
    },
    "MANAUS_Trade":{
        "MANAUS_Agriculture":0.059395135,
        "MANAUS_Mining":0.031209898,
        "MANAUS_Manufacturing":0.0206510625,
        "MANAUS_Utilities":0.020162528,
        "MANAUS_Construction":0.0173718119,
        "MANAUS_Trade":0.0272572721,
        "MANAUS_Transport":0.0123465541,
        "MANAUS_Business":0.0029982061,
        "MANAUS_Financial":0.00593415,
        "MANAUS_RealEstate":0.003260666,
        "MANAUS_OtherServices":0.0098107615,
        "MANAUS_Government":0.013314366,
        "RestBR_Agriculture":0.0,
        "RestBR_Mining":0.0,
        "RestBR_Manufacturing":0.0404274364,
        "RestBR_Utilities":0.0,
        "RestBR_Construction":0.036546077,
        "RestBR_Trade":0.0,
        "RestBR_Transport":0.0240088877,
        "RestBR_Business":0.0209185328,
        "RestBR_Financial":0.0008165033,
        "RestBR_RealEstate":0.0,
        "RestBR_OtherServices":0.0221713822,
        "RestBR_Government":0.0
    },
    "MANAUS_Transport":{
        "MANAUS_Agriculture":0.019993629,
        "MANAUS_Mining":0.083783137,
        "MANAUS_Manufacturing":0.049323146,
        "MANAUS_Utilities":0.018608535,
        "MANAUS_Construction":0.011904719,
        "MANAUS_Trade":0.050342209,
        "MANAUS_Transport":0.112530531,
        "MANAUS_Business":0.0059498199,
        "MANAUS_Financial":0.014215252,
        "MANAUS_RealEstate":0.000853874,
        "MANAUS_OtherServices":0.018312787,
        "MANAUS_Government":0.011772526,
        "RestBR_Agriculture":0.0,
        "RestBR_Mining":0.0,
        "RestBR_Manufacturing":0.0,
        "RestBR_Utilities":0.0,
        "RestBR_Construction":0.0,
        "RestBR_Trade":0.0,
        "RestBR_Transport":0.0,
        "RestBR_Business":0.0047133789,
        "RestBR_Financial":0.0,
        "RestBR_RealEstate":0.0,
        "RestBR_OtherServices":0.0005349984,
        "RestBR_Government":0.0
    },
    "MANAUS_Business":{
        "MANAUS_Agriculture":0.000201581,
        "MANAUS_Mining":0.003878988,
        "MANAUS_Manufacturing":0.005629733,
        "MANAUS_Utilities":0.006543292,
        "MANAUS_Construction":0.002253644,
        "MANAUS_Trade":0.013107921,
        "MANAUS_Transport":0.007641952,
        "MANAUS_Business":0.120957886,
        "MANAUS_Financial":0.039272538,
        "MANAUS_RealEstate":0.001419554,
        "MANAUS_OtherServices":0.037999555,
        "MANAUS_Government":0.017331599,
        "RestBR_Agriculture":0.0,
        "RestBR_Mining":0.0,
        "RestBR_Manufacturing":0.0,
        "RestBR_Utilities":0.0,
        "RestBR_Construction":0.0,
        "RestBR_Trade":0.0,
        "RestBR_Transport":0.0,
        "RestBR_Business":0.0,
        "RestBR_Financial":0.0,
        "RestBR_RealEstate":0.0,
        "RestBR_OtherServices":0.0,
        "RestBR_Government":0.0
    },
    "MANAUS_Financial":{
        "MANAUS_Agriculture":0.015253392,
        "MANAUS_Mining":0.022241782,
        "MANAUS_Manufacturing":0.0050844677,
        "MANAUS_Utilities":0.021695073,
        "MANAUS_Construction":0.0047567221,
        "MANAUS_Trade":0.023598441,
        "MANAUS_Transport":0.0072022127,
        "MANAUS_Business":0.0038652335,
        "MANAUS_Financial":0.124072904,
        "MANAUS_RealEstate":0.037904361,
        "MANAUS_OtherServices":0.0057486047,
        "MANAUS_Government":0.044627956,
        "RestBR_Agriculture":0.0,
        "RestBR_Mining":0.0,
        "RestBR_Manufacturing":0.0023189911,
        "RestBR_Utilities":0.0,
        "RestBR_Construction":0.0049583719,
        "RestBR_Trade":0.0,
        "RestBR_Transport":0.0032072458,
        "RestBR_Business":0.0206776435,
        "RestBR_Financial":0.0,
        "RestBR_RealEstate":0.0,
        "RestBR_OtherServices":0.0076409091,
        "RestBR_Government":0.0
    },
    "MANAUS_RealEstate":{
        "MANAUS_Agriculture":0.0000364576,
        "MANAUS_Mining":0.001358359,
        "MANAUS_Manufacturing":0.0000582481,
        "MANAUS_Utilities":0.0018038852,
        "MANAUS_Construction":0.0000614857,
        "MANAUS_Trade":0.0055549551,
        "MANAUS_Transport":0.0002149997,
        "MANAUS_Business":0.000178388,
        "MANAUS_Financial":0.0014277265,
        "MANAUS_RealEstate":0.0003303269,
        "MANAUS_OtherServices":0.0006500739,
        "MANAUS_Government":0.0004822762,
        "RestBR_Agriculture":0.0,
        "RestBR_Mining":0.0,
        "RestBR_Manufacturing":0.0015904972,
        "RestBR_Utilities":0.0,
        "RestBR_Construction":0.0015146216,
        "RestBR_Trade":0.0198402972,
        "RestBR_Transport":0.0058457035,
        "RestBR_Business":0.0116943928,
        "RestBR_Financial":0.0073826992,
        "RestBR_RealEstate":0.0016759108,
        "RestBR_OtherServices":0.0160413338,
        "RestBR_Government":0.001703412
    },
    "MANAUS_OtherServices":{
        "MANAUS_Agriculture":0.00369196,
        "MANAUS_Mining":0.092964573,
        "MANAUS_Manufacturing":0.045851826,
        "MANAUS_Utilities":0.050632926,
        "MANAUS_Construction":0.023313871,
        "MANAUS_Trade":0.079917796,
        "MANAUS_Transport":0.057672585,
        "MANAUS_Business":0.0745957172,
        "MANAUS_Financial":0.101801513,
        "MANAUS_RealEstate":0.007998258,
        "MANAUS_OtherServices":0.090339152,
        "MANAUS_Government":0.078202142,
        "RestBR_Agriculture":0.0,
        "RestBR_Mining":0.0,
        "RestBR_Manufacturing":0.0,
        "RestBR_Utilities":0.0,
        "RestBR_Construction":0.0,
        "RestBR_Trade":0.0,
        "RestBR_Transport":0.0,
        "RestBR_Business":0.0269855459,
        "RestBR_Financial":0.0,
        "RestBR_RealEstate":0.0,
        "RestBR_OtherServices":0.0,
        "RestBR_Government":0.0
    },
    "MANAUS_Government":{
        "MANAUS_Agriculture":0.00074141,
        "MANAUS_Mining":0.004864058,
        "MANAUS_Manufacturing":0.0008995218,
        "MANAUS_Utilities":0.004594445,
        "MANAUS_Construction":0.0004333752,
        "MANAUS_Trade":0.004107293,
        "MANAUS_Transport":0.0012549254,
        "MANAUS_Business":0.0009307942,
        "MANAUS_Financial":0.004482879,
        "MANAUS_RealEstate":0.000377111,
        "MANAUS_OtherServices":0.0015627369,
        "MANAUS_Government":0.0034693898,
        "RestBR_Agriculture":0.0,
        "RestBR_Mining":0.0,
        "RestBR_Manufacturing":0.0017295565,
        "RestBR_Utilities":0.0,
        "RestBR_Construction":0.0008355859,
        "RestBR_Trade":0.0,
        "RestBR_Transport":0.002399238,
        "RestBR_Business":0.0055111442,
        "RestBR_Financial":0.0014541395,
        "RestBR_RealEstate":0.0,
        "RestBR_OtherServices":0.0031548585,
        "RestBR_Government":0.0
    },
    "RestBR_Agriculture":{
        "MANAUS_Agriculture":0.0393691106,
        "MANAUS_Mining":0.0,
        "MANAUS_Manufacturing":0.0758688502,
        "MANAUS_Utilities":0.0004169267,
        "MANAUS_Construction":0.0025369292,
        "MANAUS_Trade":0.0087892705,
        "MANAUS_Transport":0.0005639879,
        "MANAUS_Business":0.0002389036,
        "MANAUS_Financial":0.0000603486,
        "MANAUS_RealEstate":0.0000372707,
        "MANAUS_OtherServices":0.0042929201,
        "MANAUS_Government":0.0015178759,
        "RestBR_Agriculture":0.0170996225,
        "RestBR_Mining":0.000524637,
        "RestBR_Manufacturing":0.0108882482,
        "RestBR_Utilities":0.000463372,
        "RestBR_Construction":0.0002741942,
        "RestBR_Trade":0.0041013566,
        "RestBR_Transport":0.0000811878,
        "RestBR_Business":0.0000114019,
        "RestBR_Financial":0.0000157596,
        "RestBR_RealEstate":0.0000550125,
        "RestBR_OtherServices":0.0003913205,
        "RestBR_Government":0.0008973049
    },
    "RestBR_Mining":{
        "MANAUS_Agriculture":0.0007630657,
        "MANAUS_Mining":0.0540444353,
        "MANAUS_Manufacturing":0.0420049497,
        "MANAUS_Utilities":0.0145727183,
        "MANAUS_Construction":0.0111654845,
        "MANAUS_Trade":0.0001873375,
        "MANAUS_Transport":0.0002831132,
        "MANAUS_Business":0.000288325,
        "MANAUS_Financial":0.0000779203,
        "MANAUS_RealEstate":0.0005817084,
        "MANAUS_OtherServices":0.0002058082,
        "MANAUS_Government":0.0002922236,
        "RestBR_Agriculture":0.0002254482,
        "RestBR_Mining":0.0030561622,
        "RestBR_Manufacturing":0.000798075,
        "RestBR_Utilities":0.00338927,
        "RestBR_Construction":0.0001596212,
        "RestBR_Trade":0.0000112859,
        "RestBR_Transport":0.0000053954,
        "RestBR_Business":0.0000018276,
        "RestBR_Financial":0.000002635,
        "RestBR_RealEstate":0.0001392474,
        "RestBR_OtherServices":0.0000024812,
        "RestBR_Government":0.000022434
    },
    "RestBR_Manufacturing":{
        "MANAUS_Agriculture":0.0,
        "MANAUS_Mining":0.0,
        "MANAUS_Manufacturing":0.0,
        "MANAUS_Utilities":0.0,
        "MANAUS_Construction":0.0,
        "MANAUS_Trade":0.0,
        "MANAUS_Transport":0.0,
        "MANAUS_Business":0.010632179,
        "MANAUS_Financial":0.0,
        "MANAUS_RealEstate":0.0,
        "MANAUS_OtherServices":0.0,
        "MANAUS_Government":0.0,
        "RestBR_Agriculture":0.20642303,
        "RestBR_Mining":0.110894505,
        "RestBR_Manufacturing":0.273069483,
        "RestBR_Utilities":0.075992549,
        "RestBR_Construction":0.205220303,
        "RestBR_Trade":0.057380844,
        "RestBR_Transport":0.182534981,
        "RestBR_Business":0.0143261952,
        "RestBR_Financial":0.009685629,
        "RestBR_RealEstate":0.009289329,
        "RestBR_OtherServices":0.0692381446,
        "RestBR_Government":0.025899345
    },
    "RestBR_Utilities":{
        "MANAUS_Agriculture":0.0,
        "MANAUS_Mining":0.0,
        "MANAUS_Manufacturing":0.0138734744,
        "MANAUS_Utilities":0.1688766074,
        "MANAUS_Construction":0.0010258822,
        "MANAUS_Trade":0.0082917408,
        "MANAUS_Transport":0.0051501419,
        "MANAUS_Business":0.0068998237,
        "MANAUS_Financial":0.0021478062,
        "MANAUS_RealEstate":0.0,
        "MANAUS_OtherServices":0.0146592454,
        "MANAUS_Government":0.0098284011,
        "RestBR_Agriculture":0.023301242,
        "RestBR_Mining":0.010807605,
        "RestBR_Manufacturing":0.0019799769,
        "RestBR_Utilities":0.104636609,
        "RestBR_Construction":0.0001120523,
        "RestBR_Trade":0.0070931422,
        "RestBR_Transport":0.000737559,
        "RestBR_Business":0.0003097019,
        "RestBR_Financial":0.0009318207,
        "RestBR_RealEstate":0.001259522,
        "RestBR_OtherServices":0.0013530077,
        "RestBR_Government":0.0088827313
    },
    "RestBR_Construction":{
        "MANAUS_Agriculture":0.0,
        "MANAUS_Mining":0.0,
        "MANAUS_Manufacturing":0.0,
        "MANAUS_Utilities":0.0,
        "MANAUS_Construction":0.0,
        "MANAUS_Trade":0.0,
        "MANAUS_Transport":0.0,
        "MANAUS_Business":0.0075497696,
        "MANAUS_Financial":0.0,
        "MANAUS_RealEstate":0.0,
        "MANAUS_OtherServices":0.0,
        "MANAUS_Government":0.0,
        "RestBR_Agriculture":0.000592695,
        "RestBR_Mining":0.012571096,
        "RestBR_Manufacturing":0.000917125,
        "RestBR_Utilities":0.012761137,
        "RestBR_Construction":0.093540153,
        "RestBR_Trade":0.001035306,
        "RestBR_Transport":0.003140253,
        "RestBR_Business":0.0111542747,
        "RestBR_Financial":0.002982811,
        "RestBR_RealEstate":0.002920853,
        "RestBR_OtherServices":0.003560329,
        "RestBR_Government":0.013924249
    },
    "RestBR_Trade":{
        "MANAUS_Agriculture":0.0,
        "MANAUS_Mining":0.0,
        "MANAUS_Manufacturing":0.0582512595,
        "MANAUS_Utilities":0.0,
        "MANAUS_Construction":0.0403458381,
        "MANAUS_Trade":0.0002475099,
        "MANAUS_Transport":0.0346471399,
        "MANAUS_Business":0.0219891039,
        "MANAUS_Financial":0.0,
        "MANAUS_RealEstate":0.0,
        "MANAUS_OtherServices":0.0222902815,
        "MANAUS_Government":0.0,
        "RestBR_Agriculture":0.059395135,
        "RestBR_Mining":0.031209898,
        "RestBR_Manufacturing":0.0384748856,
        "RestBR_Utilities":0.020162528,
        "RestBR_Construction":0.021171573,
        "RestBR_Trade":0.027504782,
        "RestBR_Transport":0.0229848063,
        "RestBR_Business":0.0040687772,
        "RestBR_Financial":0.0051176467,
        "RestBR_RealEstate":0.003260666,
        "RestBR_OtherServices":0.0099296608,
        "RestBR_Government":0.013314366
    },
    "RestBR_Transport":{
        "MANAUS_Agriculture":0.0,
        "MANAUS_Mining":0.0,
        "MANAUS_Manufacturing":0.0,
        "MANAUS_Utilities":0.0,
        "MANAUS_Construction":0.0,
        "MANAUS_Trade":0.0,
        "MANAUS_Transport":0.0,
        "MANAUS_Business":0.0036897231,
        "MANAUS_Financial":0.0,
        "MANAUS_RealEstate":0.0,
        "MANAUS_OtherServices":0.0,
        "MANAUS_Government":0.0,
        "RestBR_Agriculture":0.019993629,
        "RestBR_Mining":0.083783137,
        "RestBR_Manufacturing":0.049323146,
        "RestBR_Utilities":0.018608535,
        "RestBR_Construction":0.011904719,
        "RestBR_Trade":0.050342209,
        "RestBR_Transport":0.112530531,
        "RestBR_Business":0.0049261641,
        "RestBR_Financial":0.014215252,
        "RestBR_RealEstate":0.000853874,
        "RestBR_OtherServices":0.0177777886,
        "RestBR_Government":0.011772526
    },
    "RestBR_Business":{
        "MANAUS_Agriculture":0.0,
        "MANAUS_Mining":0.0,
        "MANAUS_Manufacturing":0.0,
        "MANAUS_Utilities":0.0,
        "MANAUS_Construction":0.0,
        "MANAUS_Trade":0.0,
        "MANAUS_Transport":0.0,
        "MANAUS_Business":0.0,
        "MANAUS_Financial":0.0,
        "MANAUS_RealEstate":0.0,
        "MANAUS_OtherServices":0.0,
        "MANAUS_Government":0.0,
        "RestBR_Agriculture":0.000201581,
        "RestBR_Mining":0.003878988,
        "RestBR_Manufacturing":0.005629733,
        "RestBR_Utilities":0.006543292,
        "RestBR_Construction":0.002253644,
        "RestBR_Trade":0.013107921,
        "RestBR_Transport":0.007641952,
        "RestBR_Business":0.120957886,
        "RestBR_Financial":0.039272538,
        "RestBR_RealEstate":0.001419554,
        "RestBR_OtherServices":0.037999555,
        "RestBR_Government":0.017331599
    },
    "RestBR_Financial":{
        "MANAUS_Agriculture":0.0,
        "MANAUS_Mining":0.0,
        "MANAUS_Manufacturing":0.0124744303,
        "MANAUS_Utilities":0.0,
        "MANAUS_Construction":0.0095281279,
        "MANAUS_Trade":0.0,
        "MANAUS_Transport":0.0175756673,
        "MANAUS_Business":0.0252511975,
        "MANAUS_Financial":0.0,
        "MANAUS_RealEstate":0.0,
        "MANAUS_OtherServices":0.0112527393,
        "MANAUS_Government":0.0,
        "RestBR_Agriculture":0.015253392,
        "RestBR_Mining":0.022241782,
        "RestBR_Manufacturing":0.0152399069,
        "RestBR_Utilities":0.021695073,
        "RestBR_Construction":0.0093264781,
        "RestBR_Trade":0.023598441,
        "RestBR_Transport":0.0215706342,
        "RestBR_Business":0.0084387875,
        "RestBR_Financial":0.124072904,
        "RestBR_RealEstate":0.037904361,
        "RestBR_OtherServices":0.0093604349,
        "RestBR_Government":0.044627956
    },
    "RestBR_RealEstate":{
        "MANAUS_Agriculture":0.0,
        "MANAUS_Mining":0.0,
        "MANAUS_Manufacturing":0.0017725949,
        "MANAUS_Utilities":0.0024907188,
        "MANAUS_Construction":0.0016190953,
        "MANAUS_Trade":0.0282586199,
        "MANAUS_Transport":0.0065171513,
        "MANAUS_Business":0.012052157,
        "MANAUS_Financial":0.0081873155,
        "MANAUS_RealEstate":0.0024118271,
        "MANAUS_OtherServices":0.0168484441,
        "MANAUS_Government":0.0031227508,
        "RestBR_Agriculture":0.0000364576,
        "RestBR_Mining":0.001358359,
        "RestBR_Manufacturing":0.0002403458,
        "RestBR_Utilities":0.004294604,
        "RestBR_Construction":0.0001659594,
        "RestBR_Trade":0.0139732778,
        "RestBR_Transport":0.0008864475,
        "RestBR_Business":0.0005361522,
        "RestBR_Financial":0.0022323428,
        "RestBR_RealEstate":0.0010662432,
        "RestBR_OtherServices":0.0014571842,
        "RestBR_Government":0.001901615
    },
    "RestBR_OtherServices":{
        "MANAUS_Agriculture":0.0,
        "MANAUS_Mining":0.0,
        "MANAUS_Manufacturing":0.0,
        "MANAUS_Utilities":0.0,
        "MANAUS_Construction":0.0,
        "MANAUS_Trade":0.0,
        "MANAUS_Transport":0.0,
        "MANAUS_Business":0.0659908768,
        "MANAUS_Financial":0.0,
        "MANAUS_RealEstate":0.0,
        "MANAUS_OtherServices":0.0,
        "MANAUS_Government":0.0,
        "RestBR_Agriculture":0.00369196,
        "RestBR_Mining":0.092964573,
        "RestBR_Manufacturing":0.045851826,
        "RestBR_Utilities":0.050632926,
        "RestBR_Construction":0.023313871,
        "RestBR_Trade":0.079917796,
        "RestBR_Transport":0.057672585,
        "RestBR_Business":0.1136010481,
        "RestBR_Financial":0.101801513,
        "RestBR_RealEstate":0.007998258,
        "RestBR_OtherServices":0.090339152,
        "RestBR_Government":0.078202142
    },
    "RestBR_Government":{
        "MANAUS_Agriculture":0.0,
        "MANAUS_Mining":0.0,
        "MANAUS_Manufacturing":0.0018991822,
        "MANAUS_Utilities":0.0,
        "MANAUS_Construction":0.0007391588,
        "MANAUS_Trade":0.0,
        "MANAUS_Transport":0.0026347166,
        "MANAUS_Business":0.0053861868,
        "MANAUS_Financial":0.0,
        "MANAUS_RealEstate":0.0,
        "MANAUS_OtherServices":0.0026011621,
        "MANAUS_Government":0.0,
        "RestBR_Agriculture":0.00074141,
        "RestBR_Mining":0.004864058,
        "RestBR_Manufacturing":0.0010691475,
        "RestBR_Utilities":0.004594445,
        "RestBR_Construction":0.0003369481,
        "RestBR_Trade":0.004107293,
        "RestBR_Transport":0.001490404,
        "RestBR_Business":0.0008058368,
        "RestBR_Financial":0.0030287395,
        "RestBR_RealEstate":0.000377111,
        "RestBR_OtherServices":0.0010090405,
        "RestBR_Government":0.0034693898
    }
}