{
    "VITORIA_Agriculture":{
        "VITORIA_Export":0.0505494181,
        "VITORIA_GovernmentConsumption":0.000192965,
        "VITORIA_ConsumptionNGOs":0.0,
        "VITORIA_HouseholdConsumption":0.4258233175,
        "VITORIA_FBCFixo":0.0609356048,
        "RestBR_Export":0.4797185276,
        "RestBR_GovernmentConsumption":0.0,
        "RestBR_ConsumptionNGOs":0.0,
        "RestBR_HouseholdConsumption":0.0,
        "RestBR_FBCFixo":0.0
    },
    "VITORIA_Mining":{
        "VITORIA_Export":0.4354168334,
        "VITORIA_GovernmentConsumption":0.0,
        "VITORIA_ConsumptionNGOs":0.0,
        "VITORIA_HouseholdConsumption":0.0,
        "VITORIA_FBCFixo":0.0792178305,
        "RestBR_Export":0.4254144534,
        "RestBR_GovernmentConsumption":0.0,
        "RestBR_ConsumptionNGOs":0.0,
        "RestBR_HouseholdConsumption":0.0,
        "RestBR_FBCFixo":0.0
    },
    "VITORIA_Manufacturing":{
        "VITORIA_Export":0.1860266297,
        "VITORIA_GovernmentConsumption":0.0031928989,
        "VITORIA_ConsumptionNGOs":0.0,
        "VITORIA_HouseholdConsumption":0.5724677527,
        "VITORIA_FBCFixo":0.1422700924,
        "RestBR_Export":0.113176125,
        "RestBR_GovernmentConsumption":0.0,
        "RestBR_ConsumptionNGOs":0.0,
        "RestBR_HouseholdConsumption":0.0,
        "RestBR_FBCFixo":0.0
    },
    "VITORIA_Utilities":{
        "VITORIA_Export":0.0000154368,
        "VITORIA_GovernmentConsumption":0.0,
        "VITORIA_ConsumptionNGOs":0.0,
        "VITORIA_HouseholdConsumption":0.9956038504,
        "VITORIA_FBCFixo":0.0,
        "RestBR_Export":0.0000242576,
        "RestBR_GovernmentConsumption":0.0,
        "RestBR_ConsumptionNGOs":0.0,
        "RestBR_HouseholdConsumption":0.0,
        "RestBR_FBCFixo":0.0
    },
    "VITORIA_Construction":{
        "VITORIA_Export":0.0054557152,
        "VITORIA_GovernmentConsumption":0.0,
        "VITORIA_ConsumptionNGOs":0.0,
        "VITORIA_HouseholdConsumption":0.0,
        "VITORIA_FBCFixo":0.9912930344,
        "RestBR_Export":0.0032512504,
        "RestBR_GovernmentConsumption":0.0,
        "RestBR_ConsumptionNGOs":0.0,
        "RestBR_HouseholdConsumption":0.0,
        "RestBR_FBCFixo":0.0
    },
    "VITORIA_Trade":{
        "VITORIA_Export":0.0076013749,
        "VITORIA_GovernmentConsumption":0.0053143586,
        "VITORIA_ConsumptionNGOs":0.0,
        "VITORIA_HouseholdConsumption":0.8770458483,
        "VITORIA_FBCFixo":0.0916199178,
        "RestBR_Export":0.0184185004,
        "RestBR_GovernmentConsumption":0.0,
        "RestBR_ConsumptionNGOs":0.0,
        "RestBR_HouseholdConsumption":0.0,
        "RestBR_FBCFixo":0.0
    },
    "VITORIA_Transport":{
        "VITORIA_Export":0.1119427681,
        "VITORIA_GovernmentConsumption":0.0004101234,
        "VITORIA_ConsumptionNGOs":0.0,
        "VITORIA_HouseholdConsumption":0.8162845463,
        "VITORIA_FBCFixo":0.0279677722,
        "RestBR_Export":0.0433947899,
        "RestBR_GovernmentConsumption":0.0,
        "RestBR_ConsumptionNGOs":0.0,
        "RestBR_HouseholdConsumption":0.0,
        "RestBR_FBCFixo":0.0
    },
    "VITORIA_Business":{
        "VITORIA_Export":0.0212883526,
        "VITORIA_GovernmentConsumption":0.0,
        "VITORIA_ConsumptionNGOs":0.0,
        "VITORIA_HouseholdConsumption":0.597303194,
        "VITORIA_FBCFixo":0.3617737878,
        "RestBR_Export":0.0187703048,
        "RestBR_GovernmentConsumption":0.0,
        "RestBR_ConsumptionNGOs":0.0,
        "RestBR_HouseholdConsumption":0.0,
        "RestBR_FBCFixo":0.0
    },
    "VITORIA_Financial":{
        "VITORIA_Export":0.0507305626,
        "VITORIA_GovernmentConsumption":0.0071596118,
        "VITORIA_ConsumptionNGOs":0.0,
        "VITORIA_HouseholdConsumption":0.9419275935,
        "VITORIA_FBCFixo":0.0,
        "RestBR_Export":0.0001822322,
        "RestBR_GovernmentConsumption":0.0,
        "RestBR_ConsumptionNGOs":0.0,
        "RestBR_HouseholdConsumption":0.0,
        "RestBR_FBCFixo":0.0
    },
    "VITORIA_Realestate":{
        "VITORIA_Export":0.0062546137,
        "VITORIA_GovernmentConsumption":0.0,
        "VITORIA_ConsumptionNGOs":0.0,
        "VITORIA_HouseholdConsumption":0.9887665251,
        "VITORIA_FBCFixo":0.0,
        "RestBR_Export":0.0049788612,
        "RestBR_GovernmentConsumption":0.0,
        "RestBR_ConsumptionNGOs":0.0,
        "RestBR_HouseholdConsumption":0.0,
        "RestBR_FBCFixo":0.0
    },
    "VITORIA_OtherServices":{
        "VITORIA_Export":0.0686458411,
        "VITORIA_GovernmentConsumption":0.0400141397,
        "VITORIA_ConsumptionNGOs":0.0995740993,
        "VITORIA_HouseholdConsumption":0.7340714852,
        "VITORIA_FBCFixo":0.0576944348,
        "RestBR_Export":0.0,
        "RestBR_GovernmentConsumption":0.0,
        "RestBR_ConsumptionNGOs":0.0,
        "RestBR_HouseholdConsumption":0.0,
        "RestBR_FBCFixo":0.0
    },
    "VITORIA_Government":{
        "VITORIA_Export":0.0,
        "VITORIA_GovernmentConsumption":1.0,
        "VITORIA_ConsumptionNGOs":0.0,
        "VITORIA_HouseholdConsumption":0.0,
        "VITORIA_FBCFixo":0.0,
        "RestBR_Export":0.0,
        "RestBR_GovernmentConsumption":0.0,
        "RestBR_ConsumptionNGOs":0.0,
        "RestBR_HouseholdConsumption":0.0,
        "RestBR_FBCFixo":0.0
    },
    "RestBR_Agriculture":{
        "VITORIA_Export":0.0,
        "VITORIA_GovernmentConsumption":0.0,
        "VITORIA_ConsumptionNGOs":0.0,
        "VITORIA_HouseholdConsumption":0.0,
        "VITORIA_FBCFixo":0.0,
        "RestBR_Export":0.5302679457,
        "RestBR_GovernmentConsumption":0.000192965,
        "RestBR_ConsumptionNGOs":0.0,
        "RestBR_HouseholdConsumption":0.4258233175,
        "RestBR_FBCFixo":0.0609356048
    },
    "RestBR_Mining":{
        "VITORIA_Export":0.0003418796,
        "VITORIA_GovernmentConsumption":0.0,
        "VITORIA_ConsumptionNGOs":0.0,
        "VITORIA_HouseholdConsumption":0.0,
        "VITORIA_FBCFixo":0.0,
        "RestBR_Export":0.8604894071,
        "RestBR_GovernmentConsumption":0.0,
        "RestBR_ConsumptionNGOs":0.0,
        "RestBR_HouseholdConsumption":0.0,
        "RestBR_FBCFixo":0.0792178305
    },
    "RestBR_Manufacturing":{
        "VITORIA_Export":0.0009267951,
        "VITORIA_GovernmentConsumption":0.0,
        "VITORIA_ConsumptionNGOs":0.0,
        "VITORIA_HouseholdConsumption":0.0,
        "VITORIA_FBCFixo":0.0,
        "RestBR_Export":0.2982759596,
        "RestBR_GovernmentConsumption":0.0031928989,
        "RestBR_ConsumptionNGOs":0.0,
        "RestBR_HouseholdConsumption":0.5724677527,
        "RestBR_FBCFixo":0.1422700924
    },
    "RestBR_Utilities":{
        "VITORIA_Export":0.0,
        "VITORIA_GovernmentConsumption":0.0,
        "VITORIA_ConsumptionNGOs":0.0,
        "VITORIA_HouseholdConsumption":0.0,
        "VITORIA_FBCFixo":0.0,
        "RestBR_Export":0.0000396944,
        "RestBR_GovernmentConsumption":0.0,
        "RestBR_ConsumptionNGOs":0.0,
        "RestBR_HouseholdConsumption":0.9956038504,
        "RestBR_FBCFixo":0.0
    },
    "RestBR_Construction":{
        "VITORIA_Export":0.0000279541,
        "VITORIA_GovernmentConsumption":0.0,
        "VITORIA_ConsumptionNGOs":0.0,
        "VITORIA_HouseholdConsumption":0.0,
        "VITORIA_FBCFixo":0.0,
        "RestBR_Export":0.0086790115,
        "RestBR_GovernmentConsumption":0.0,
        "RestBR_ConsumptionNGOs":0.0,
        "RestBR_HouseholdConsumption":0.0,
        "RestBR_FBCFixo":0.9912930344
    },
    "RestBR_Trade":{
        "VITORIA_Export":0.0,
        "VITORIA_GovernmentConsumption":0.0,
        "VITORIA_ConsumptionNGOs":0.0,
        "VITORIA_HouseholdConsumption":0.0,
        "VITORIA_FBCFixo":0.0,
        "RestBR_Export":0.0260198753,
        "RestBR_GovernmentConsumption":0.0053143586,
        "RestBR_ConsumptionNGOs":0.0,
        "RestBR_HouseholdConsumption":0.8770458483,
        "RestBR_FBCFixo":0.0916199178
    },
    "RestBR_Transport":{
        "VITORIA_Export":0.0008390182,
        "VITORIA_GovernmentConsumption":0.0,
        "VITORIA_ConsumptionNGOs":0.0,
        "VITORIA_HouseholdConsumption":0.0,
        "VITORIA_FBCFixo":0.0,
        "RestBR_Export":0.1544985399,
        "RestBR_GovernmentConsumption":0.0004101234,
        "RestBR_ConsumptionNGOs":0.0,
        "RestBR_HouseholdConsumption":0.8162845463,
        "RestBR_FBCFixo":0.0279677722
    },
    "RestBR_Business":{
        "VITORIA_Export":0.0000398149,
        "VITORIA_GovernmentConsumption":0.0,
        "VITORIA_ConsumptionNGOs":0.0,
        "VITORIA_HouseholdConsumption":0.0,
        "VITORIA_FBCFixo":0.0,
        "RestBR_Export":0.0400188424,
        "RestBR_GovernmentConsumption":0.0,
        "RestBR_ConsumptionNGOs":0.0,
        "RestBR_HouseholdConsumption":0.597303194,
        "RestBR_FBCFixo":0.3617737878
    },
    "RestBR_Financial":{
        "VITORIA_Export":0.0006020436,
        "VITORIA_GovernmentConsumption":0.0,
        "VITORIA_ConsumptionNGOs":0.0,
        "VITORIA_HouseholdConsumption":0.0,
        "VITORIA_FBCFixo":0.0,
        "RestBR_Export":0.0503107512,
        "RestBR_GovernmentConsumption":0.0071596118,
        "RestBR_ConsumptionNGOs":0.0,
        "RestBR_HouseholdConsumption":0.9419275935,
        "RestBR_FBCFixo":0.0
    },
    "RestBR_Realestate":{
        "VITORIA_Export":0.0000177993,
        "VITORIA_GovernmentConsumption":0.0,
        "VITORIA_ConsumptionNGOs":0.0,
        "VITORIA_HouseholdConsumption":0.0,
        "VITORIA_FBCFixo":0.0,
        "RestBR_Export":0.0112156756,
        "RestBR_GovernmentConsumption":0.0,
        "RestBR_ConsumptionNGOs":0.0,
        "RestBR_HouseholdConsumption":0.9887665251,
        "RestBR_FBCFixo":0.0
    },
    "RestBR_OtherServices":{
        "VITORIA_Export":0.0015961386,
        "VITORIA_GovernmentConsumption":0.0,
        "VITORIA_ConsumptionNGOs":0.0,
        "VITORIA_HouseholdConsumption":0.0,
        "VITORIA_FBCFixo":0.0,
        "RestBR_Export":0.0670497024,
        "RestBR_GovernmentConsumption":0.0400141397,
        "RestBR_ConsumptionNGOs":0.0995740993,
        "RestBR_HouseholdConsumption":0.7340714852,
        "RestBR_FBCFixo":0.0576944348
    },
    "RestBR_Government":{
        "VITORIA_Export":0.0,
        "VITORIA_GovernmentConsumption":0.0,
        "VITORIA_ConsumptionNGOs":0.0,
        "VITORIA_HouseholdConsumption":0.0,
        "VITORIA_FBCFixo":0.0,
        "RestBR_Export":0.0,
        "RestBR_GovernmentConsumption":1.0,
        "RestBR_ConsumptionNGOs":0.0,
        "RestBR_HouseholdConsumption":0.0,
        "RestBR_FBCFixo":0.0
    }
}